polyga/__init__.py
polyga/analysis/__init__.py
polyga/default_files/dna.csv
polyga/models.py
polyga/polygod.py
polyga/selection_schemes.py
polyga/utils.py
polyga-1.0.12.dist-info/LICENSE
polyga-1.0.12.dist-info/WHEEL
polyga-1.0.12.dist-info/METADATA
polyga-1.0.12.dist-info/RECORD
